AutoDiff/ForwardAD.py
AutoDiff/__init__.py
AutoDiff/optimize.py
AutoDiff/root_finding.py
test/__init__.py
test/test_ForwardAD.py
test/test_optimize.py
test/test_root.py
AutoDifferentiate-1.0.0.dist-info/LICENSE
AutoDifferentiate-1.0.0.dist-info/METADATA
AutoDifferentiate-1.0.0.dist-info/WHEEL
AutoDifferentiate-1.0.0.dist-info/top_level.txt
AutoDifferentiate-1.0.0.dist-info/RECORD
