Metadata-Version: 2.1
Name: AutoDifferentiate
Version: 1.0.0
Summary: An AutoDifferentiation package
Home-page: https://github.com/BackPropagators/cs207-FinalProject.git
Author: Lihong Zhang, Yichen Geng, Yingsi Jian, Matthieu Meeus  
License: UNKNOWN
Platform: UNKNOWN
Classifier: Programming Language :: Python :: 3
Classifier: License :: OSI Approved :: MIT License
Classifier: Operating System :: OS Independent
Requires-Dist: certifi (==2019.9.11)
Requires-Dist: wincertstore (==0.2)
Requires-Dist: numpy (==1.17.4)
